ipypb/__init__.py
ipypb/progressbar.py
ipypb-0.5.2.dist-info/LICENSE
ipypb-0.5.2.dist-info/METADATA
ipypb-0.5.2.dist-info/WHEEL
ipypb-0.5.2.dist-info/top_level.txt
ipypb-0.5.2.dist-info/RECORD
