Metadata-Version: 2.1
Name: ipypb
Version: 0.5.2
Summary: Interactive ProgressBar natively built with IPython
Home-page: UNKNOWN
Author: Evgeny Frolov
License: UNKNOWN
Keywords: progressbar
Platform: any
Classifier: Programming Language :: Python :: 3
Classifier: License :: OSI Approved :: MIT License
Classifier: Operating System :: OS Independent
